tdms_cli/__about__.py
tdms_cli/__init__.py
tdms_cli/cli.py
tdms_cli/count_tdms_content.py
tdms_cli/extract_group_as_csv.py
tdms_cli/tdms_metadata_extraction.py
tdms_cli-0.1.0.dist-info/METADATA
tdms_cli-0.1.0.dist-info/WHEEL
tdms_cli-0.1.0.dist-info/entry_points.txt
tdms_cli-0.1.0.dist-info/licenses/LICENSE
tdms_cli-0.1.0.dist-info/RECORD
